encap-0.4.data/scripts/encap
encap-0.4.data/scripts/etool
encap_lib/__init__.py
encap_lib/encap_lib.py
encap_lib/encap_settings.py
encap_lib/fabric_wrapper.py
encap_lib/gcloud.py
encap_lib/git_tracker.py
encap_lib/machines.py
encap_lib/slurm.py
encap_lib/status.py
encap-0.4.dist-info/LICENSE
encap-0.4.dist-info/METADATA
encap-0.4.dist-info/WHEEL
encap-0.4.dist-info/top_level.txt
encap-0.4.dist-info/RECORD
