Metadata-Version: 2.1
Name: encap
Version: 0.4
Summary: A Simple Tool for Managing Computational Experiments.
Home-page: https://github.com/danielalcalde/encap
Author: Daniel Alcalde Puente
Author-email: d.alcalde.puente@fz-juelich.de
License: MIT
Classifier: Programming Language :: Python :: 3
Classifier: License :: OSI Approved :: MIT License
License-File: LICENSE
Requires-Dist: pyyaml >=5.1
Requires-Dist: fabric
Requires-Dist: GitPython
Requires-Dist: psutil
Requires-Dist: tabulate
Requires-Dist: filelock
